{
  "Ads": [
    {
      "more_app"                  : "1",
      "select_main_ads"           : "ADMOB",
      "select_backup_ads"         : "APPLOVIN-M",

      "main_ads_banner"           : "ca-app-pub-2214374349425406/2610586939",
      "main_ads_intertitial"      : "ca-app-pub-2214374349425406/1297505260",
      "main_ads_native"           : "ca-app-pub-2214374349425406/8984423594",

      "open_ads"                  : "ca-app-pub-2214374349425406/3173731709x",

      "backup_ads_banner"         : "3fb8100abd34a3fb",
      "backup_ads_intertitial"    : "7fa0a8b1ca9edeeb",
      "backup_ads_native"         : "null",
      
      "initialize_sdk"            : "null",
      "initialize_sdk_backup_ads" : "null",

      "interval_intertitial"      : 5,

      "high_paying_keyword_1"     : "",
      "high_paying_keyword_2"     : "",
      "high_paying_keyword_3"     : "",
      "high_paying_keyword_4"     : "",
      "high_paying_keyword_5"     : "",

      "status_app": "0",
      "link_redirect": "null"
      }
  ]
}